pathlt/__init__.py
pathlt/__main__.py
pathlt/transforms.py
pathlt-0.2.dist-info/DESCRIPTION.rst
pathlt-0.2.dist-info/entry_points.txt
pathlt-0.2.dist-info/METADATA
pathlt-0.2.dist-info/metadata.json
pathlt-0.2.dist-info/RECORD
pathlt-0.2.dist-info/top_level.txt
pathlt-0.2.dist-info/WHEEL
