Metadata-Version: 2.0
Name: pathlt
Version: 0.2
Summary: Path Less Traveled
Home-page: https://github.com/digwanderlust/pathlt
Author: Matt Olsen
Author-email: digwanderlust@gmail.com
License: UNKNOWN
Platform: UNKNOWN
Requires-Dist: nose
Requires-Dist: coverage
Requires-Dist: python-coveralls
Requires-Dist: mock
Requires-Dist: toolz
